markdown_flow/__init__.py
markdown_flow/constants.py
markdown_flow/core.py
markdown_flow/enums.py
markdown_flow/exceptions.py
markdown_flow/llm.py
markdown_flow/models.py
markdown_flow/utils.py
markdown_flow/parser/__init__.py
markdown_flow/parser/code_fence_utils.py
markdown_flow/parser/html_comment_utils.py
markdown_flow/parser/interaction.py
markdown_flow/parser/json_parser.py
markdown_flow/parser/output.py
markdown_flow/parser/preprocessor.py
markdown_flow/parser/validation.py
markdown_flow/parser/variable.py
markdown_flow/providers/__init__.py
markdown_flow/providers/config.py
markdown_flow/providers/openai.py
markdown_flow-0.2.43.dist-info/licenses/LICENSE
markdown_flow-0.2.43.dist-info/METADATA
markdown_flow-0.2.43.dist-info/WHEEL
markdown_flow-0.2.43.dist-info/top_level.txt
markdown_flow-0.2.43.dist-info/RECORD
