Metadata-Version: 2.4
Name: markdown-flow
Version: 0.2.43
Summary: An agent library designed to parse and process MarkdownFlow documents
Project-URL: Homepage, https://github.com/ai-shifu/markdown-flow-agent-py
Project-URL: Bug Tracker, https://github.com/ai-shifu/markdown-flow-agent-py/issues
Classifier: Development Status :: 3 - Alpha
Classifier: Intended Audience :: Developers
Classifier: License :: OSI Approved :: MIT License
Classifier: Programming Language :: Python :: 3
Classifier: Programming Language :: Python :: 3.10
Classifier: Programming Language :: Python :: 3.11
Classifier: Programming Language :: Python :: 3.12
Requires-Python: >=3.10
License-File: LICENSE
Dynamic: license-file
